{
    "communicationNumber": "ComNr_0017",
    "requester": "Financial_Institution",
    "operationExtId": "Op_0017",
    "operationType": "PIS",
    "riskManagementCategory": "OP_DEFAULT",
    "sourceOfRiskLevel": "IMPORT",
    "operationStatus":"EXECUTED",
    "riskLevel": "LOW",
    "operationDateTime": "2023-09-22T15:09:33+02:00",
    "currency": "EUR",
    "amount": 550,
    "financialFlowDirection": "INCOMING",
    "description": "invoice '123456'",
    "listOperationParty": [
         {
            "partyRole": "CREDITOR",
            "accountNumber": "LV5630800200000018112",
            "bic": "BICXX22",
            "entityType": "INDIVIDUAL",
            "firstName": "Geli",
            "lastName": "Deliono"
        }       
    ]
}